pytem1d/__init__.py
pytem1d/_version.py
pytem1d/api.py
pytem1d/core.py
pytem1d/io.py
pytem1d/models.py
pytem1d/plotting.py
pytem1d/validation.py
pytem1d/fortran/ARRAYSDIMBL.INC
pytem1d/fortran/INSTRUMENTBL.INC
pytem1d/fortran/IPBL.INC
pytem1d/fortran/MODELBL.INC
pytem1d/fortran/POLYGONBL.INC
pytem1d/fortran/RESPBL.INC
pytem1d/fortran/TEM1D.for
pytem1d/fortran/TEM1DFHT.for
pytem1d/fortran/TEM1DFUNC.for
pytem1d/fortran/TEM1DRESP.for
pytem1d/fortran/TEM1DRESPIP.for
pytem1d/fortran/TEM1DRESPPOLY.for
pytem1d/fortran/TEM1DRESPPOLYIP.for
pytem1d/fortran/WAVEBL.INC
pytem1d/lib/libtem1d.dll
pytem1d/lib/libtem1d.so
pytem1d/lib/libwinpthread-1.dll
pytem1d-0.1.2.dist-info/METADATA
pytem1d-0.1.2.dist-info/WHEEL
pytem1d-0.1.2.dist-info/top_level.txt
pytem1d-0.1.2.dist-info/RECORD
