Metadata-Version: 2.4
Name: pytem1d
Version: 0.1.2
Summary: Python interface to TEM1D Fortran code for 1D transient electromagnetic forward modeling
Author: TEM1D Contributors
License: MIT
Project-URL: Homepage, https://github.com/cultpenguin/TEM1D
Project-URL: Repository, https://github.com/cultpenguin/TEM1D
Keywords: geophysics,electromagnetics,TEM,forward-modeling,inversion
Classifier: Development Status :: 3 - Alpha
Classifier: Intended Audience :: Science/Research
Classifier: Topic :: Scientific/Engineering :: Physics
Classifier: Programming Language :: Python :: 3
Classifier: Programming Language :: Python :: 3.8
Classifier: Programming Language :: Python :: 3.9
Classifier: Programming Language :: Python :: 3.10
Classifier: Programming Language :: Python :: 3.11
Classifier: Programming Language :: Python :: 3.12
Classifier: Programming Language :: Fortran
Requires-Python: >=3.8
Requires-Dist: numpy>=1.20
Requires-Dist: matplotlib>=3.3
Provides-Extra: dev
Requires-Dist: pytest>=6.0; extra == "dev"
Requires-Dist: pytest-cov; extra == "dev"
Requires-Dist: black; extra == "dev"
Requires-Dist: mypy; extra == "dev"
Requires-Dist: ruff; extra == "dev"
